{"errors":[],"warnings":[],"namedChunkGroups":{"app":{"chunks":[6,0,2],"assets":["webpack-runtime-bca944de27b8bef20043.js","webpack-runtime-bca944de27b8bef20043.js.map","commons-43941e737877c8e0a589.js","commons-43941e737877c8e0a589.js.map","app-3abd3d03559cc8a4cb8f.js","app-3abd3d03559cc8a4cb8f.js.map"],"children":{},"childAssets":{}},"component---src-pages-404-js":{"chunks":[1,0,3],"assets":["styles.f55e3705b21bb904767f.css","styles-c5c4234a6d14e2f05fbd.js","styles-c5c4234a6d14e2f05fbd.js.map","commons-43941e737877c8e0a589.js","commons-43941e737877c8e0a589.js.map","component---src-pages-404-js-937d1b115ca56d3e6694.js","component---src-pages-404-js-937d1b115ca56d3e6694.js.map"],"children":{},"childAssets":{}},"component---src-pages-index-jsx":{"chunks":[1,0,4],"assets":["styles.f55e3705b21bb904767f.css","styles-c5c4234a6d14e2f05fbd.js","styles-c5c4234a6d14e2f05fbd.js.map","commons-43941e737877c8e0a589.js","commons-43941e737877c8e0a589.js.map","component---src-pages-index-jsx-2776e5d9b14c1cb8a15a.js","component---src-pages-index-jsx-2776e5d9b14c1cb8a15a.js.map"],"children":{},"childAssets":{}},"component---src-pages-page-2-js":{"chunks":[1,0,5],"assets":["styles.f55e3705b21bb904767f.css","styles-c5c4234a6d14e2f05fbd.js","styles-c5c4234a6d14e2f05fbd.js.map","commons-43941e737877c8e0a589.js","commons-43941e737877c8e0a589.js.map","component---src-pages-page-2-js-9091273db8b77923343d.js","component---src-pages-page-2-js-9091273db8b77923343d.js.map"],"children":{},"childAssets":{}}},"assetsByChunkName":{"app":["webpack-runtime-bca944de27b8bef20043.js","commons-43941e737877c8e0a589.js","app-3abd3d03559cc8a4cb8f.js"],"component---src-pages-404-js":["styles.f55e3705b21bb904767f.css","styles-c5c4234a6d14e2f05fbd.js","commons-43941e737877c8e0a589.js","component---src-pages-404-js-937d1b115ca56d3e6694.js"],"component---src-pages-index-jsx":["styles.f55e3705b21bb904767f.css","styles-c5c4234a6d14e2f05fbd.js","commons-43941e737877c8e0a589.js","component---src-pages-index-jsx-2776e5d9b14c1cb8a15a.js"],"component---src-pages-page-2-js":["styles.f55e3705b21bb904767f.css","styles-c5c4234a6d14e2f05fbd.js","commons-43941e737877c8e0a589.js","component---src-pages-page-2-js-9091273db8b77923343d.js"]}}